orredis-0.1.7.dist-info/METADATA
orredis-0.1.7.dist-info/WHEEL
orredis-0.1.7.dist-info/license_files/LICENSE-APACHE
orredis-0.1.7.dist-info/license_files/LICENSE-MIT
orredis/abstract.py
orredis/py.typed.py
orredis/__init__.py
orredis/orredis.pyi
orredis/orredis.cpython-38-darwin.so
orredis-0.1.7.dist-info/RECORD
