Metadata-Version: 2.1
Name: orredis
Version: 0.1.7
Classifier: Programming Language :: Rust
Classifier: Programming Language :: Python :: Implementation :: CPython
Classifier: Programming Language :: Python :: Implementation :: PyPy
Requires-Dist: pydantic>=1.10,<1.11
Requires-Dist: pytest>=7.1.3; extra == 'test'
Requires-Dist: pytest-benchmark>=3.4.1; extra == 'test'
Requires-Dist: pytest-lazy-fixture>=0.6.3; extra == 'test'
Requires-Dist: redislite>=6.2.805324; extra == 'test'
Requires-Dist: pytest-asyncio>=0.19.0; extra == 'test'
Provides-Extra: test
License-File: LICENSE-APACHE
License-File: LICENSE-MIT
Summary: A fast pydantic-based ORM for redis supporting both sync and async interaction over redis pooled connections
Keywords: redis,pydantic,orm
Author-email: Martin Ahindura  <team.sopherapps@gmail.com>
Requires-Python: >=3.7
Project-URL: changelog, https://github.com/sopherapps/orredis/blob/master/CHANGELOG.md
Project-URL: homepage, https://github.com/sopherapps/orredis
Project-URL: documentation, https://github.com/sopherapps/orredis
Project-URL: repository, https://github.com/sopherapps/orredis
